bit_seq_detector/mealy.sv
module mealy(
    input  logic clk_i,
    input  logic rstn_i,
    input  logic bit_i,
    output logic match_o
);

localparam int unsigned n_state = $clog2(3);

// states
enum logic [n_state - 1 : 0]{
    F0 = 2'b00,
    F1 = 2'b01,
    F2 = 2'b10
} state, next_state;

// next state combinational logic
always_comb begin 
    if(state == F0) begin
        if(bit_i == 0) next_state = F0;
        else next_state = F1;
    end
    else if(state == F1) begin
        if(bit_i == 0) next_state = F2;
        else next_state = F1;
    end
    else if(state == F2) begin
        if(bit_i == 0) next_state = F0;
        else next_state = F1;
    end
    else begin
        next_state = F0;
    end
end

// state sequnecer
always_ff @(posedge clk_i or negedge rstn_i) begin
    if(!rstn_i) state <= F0;
    else state <= next_state;
end

// output combinational logic
always_comb begin
    if(state == F2 && bit_i == 1) match_o = 1;
    else match_o = 0;
end
endmodule

bit_seq_detector/bit_pattern_tb.sv
`timescale 1ps/1ps  // time_unit/time_precision

module bit_pattern_tb;

logic clk_i, rstn_i, bit_i, match_o;
logic [8 - 1 : 0] test_sequence;


// design usnder test
mealy dut(
    .clk_i(clk_i),
    .rstn_i(rstn_i),
    .bit_i(bit_i),
    .match_o(match_o)
);

// clock generation
initial begin
    clk_i = 0;
    forever #5 clk_i = ~clk_i;
end

// test bench simulation
initial begin
    $dumpfile("bit_pattern_tb.vcd");
    $dumpvars(0, dut);

    rstn_i = 0;
    bit_i = 0;
    #100 rstn_i = 1;

    // define test sequence
    test_sequence = 8'b01010110;

    // apply test sequence
    for(int i = 0; i < $size(test_sequence); i++) begin
        bit_i = test_sequence[$size(test_sequence) - 1 - i];
        @(posedge clk_i);
        #1;
    end

    @(posedge clk_i);

    // stop simulation
    $finish;
end
endmodule

bit_pattern_tb.vcd
$date
	Sat Sep 12 13:28:26 2026
$end
$version
	Questa Altera Starter FPGA Edition Version 2025.2
$end
$timescale
	1ps
$end

$scope module bit_pattern_tb $end

$scope module dut $end
$var parameter 32 ! n_state $end
$var wire 1 " clk_i $end
$var wire 1 # rstn_i $end
$var wire 1 $ bit_i $end
$var reg 1 % match_o $end
$var reg 2 & state [1:0] $end
$var reg 2 ' next_state [1:0] $end
$upscope $end
$upscope $end
$enddefinitions $end
#0
$dumpvars
0%
b0 &
b0 '
b10 !
0$
0#
0"
$end
#5
1"
#10
0"
#15
1"
#20
0"
#25
1"
#30
0"
#35
1"
#40
0"
#45
1"
#50
0"
#55
1"
#60
0"
#65
1"
#70
0"
#75
1"
#80
0"
#85
1"
#90
0"
#95
1"
#100
1#
0"
#105
1"
#106
1$
b1 '
#110
0"
#115
1"
b1 &
#116
0$
b10 '
#120
0"
#125
1"
b10 &
b0 '
#126
1$
b1 '
1%
#130
0"
#135
1"
b1 &
0%
#136
0$
b10 '
#140
0"
#145
1"
b10 &
b0 '
#146
1$
b1 '
1%
#150
0"
#155
1"
b1 &
0%
#160
0"
#165
1"
#166
0$
b10 '
#170
0"
#175
1"
b10 &
b0 '
